rst_budoux/__init__.py
rst_budoux/sphinx.py
rst_budoux/cli/__init__.py
rst_budoux/cli/html.py
rst_budoux/cli/psuedoxml.py
rst_budoux/writers/__init__.py
rst_budoux/writers/html.py
rst_budoux-0.1.1.dist-info/METADATA
rst_budoux-0.1.1.dist-info/WHEEL
rst_budoux-0.1.1.dist-info/entry_points.txt
rst_budoux-0.1.1.dist-info/licenses/LICENSE.txt
rst_budoux-0.1.1.dist-info/RECORD
