Metadata-Version: 2.3
Name: rst-budoux
Version: 0.1.1
Summary: Text splitter in reStructuredText by BudouX
Project-URL: repository, https://github.com/attakei-lab/rst-budoux
Project-URL: changelog, https://github.com/attakei-lab/rst-budoux/blob/main/CHANGELOG.rst
Project-URL: documentation, https://rst-budoux.readthedocs.io/v0.1.1/
Project-URL: issues, https://github.com/attakei-lab/rst-budoux/issues
Author-email: Kazuya Takei <myself@attakei.net>
License: Apache-2.0
License-File: LICENSE.txt
Classifier: Development Status :: 3 - Alpha
Classifier: Framework :: Sphinx
Classifier: Framework :: Sphinx :: Extension
Classifier: Intended Audience :: Developers
Classifier: License :: OSI Approved :: Apache Software License
Classifier: Operating System :: OS Independent
Classifier: Programming Language :: Python
Classifier: Programming Language :: Python :: 3 :: Only
Classifier: Programming Language :: Python :: 3.9
Classifier: Programming Language :: Python :: 3.10
Classifier: Programming Language :: Python :: 3.11
Classifier: Programming Language :: Python :: 3.12
Classifier: Topic :: Documentation :: Sphinx
Classifier: Topic :: Software Development
Classifier: Topic :: Software Development :: Documentation
Requires-Python: >=3.9
Requires-Dist: budoux~=0.6.2
Requires-Dist: docutils~=0.21.2
Provides-Extra: sphinx
Requires-Dist: sphinx>=5; extra == 'sphinx'
